[
  {
    "ProfileType": "Gather",
    "GatherDistance": 10000,
    "GatherWhiteList": "Cobalt Deposit,Rich Cobalt Deposit,Goldclover,Tiger Lily",
    "CombatWhiteList": "",
    "CombatRadius": 40,
    "AutoTarget": false,
    "AutoLoot": false,
    "AutoSkin": false,
    "LoopUntilStopped": true,
    "BlackListedAreas": [
      [
        3121.92139,
        5566.92334,
        51.14561
      ]
    ],
    "BlackListCount": 1,
    "Bones": [],
    "BoneCount": 0,
    "RepairAtVendor": false,
    "RepairVendorName": null,
    "RepairAt": 30,
    "RepairVendorVec": {
      "X": 0.0,
      "Y": 0.0,
      "Z": 0.0
    },
    "SellGrays": false,
    "SellGraysAt": 2,
    "SellVendorName": null,
    "SellVendorVec": {
      "X": 0.0,
      "Y": 0.0,
      "Z": 0.0
    },
    "UseSellVendor": false,
    "PurchaseAmount": 0,
    "PurchaseVendorName": null,
    "PurchaseVendorVec": {
      "X": 0.0,
      "Y": 0.0,
      "Z": 0.0
    },
    "UsePurchaseVendor": false,
    "ItemToPurchase": null,
    "FlightPath": true,
    "FlightPathVectorCount": 149,
    "FlightPathVectors": [
      [
        4147.994,
        5297.034,
        81.21572
      ],
      [
        4140.6167,
        5323.936,
        77.39152
      ],
      [
        4112.01758,
        5448.461,
        77.5037155
      ],
      [
        4105.483,
        5573.491,
        88.26819
      ],
      [
        4194.964,
        5663.892,
        96.92028
      ],
      [
        4288.24072,
        5751.1167,
        100.801392
      ],
      [
        4392.014,
        5825.02441,
        104.937218
      ],
      [
        4511.71338,
        5855.724,
        111.419388
      ],
      [
        4614.54834,
        5917.23438,
        106.732811
      ],
      [
        4588.00732,
        6036.226,
        116.781
      ],
      [
        4548.989,
        6149.92529,
        158.37384
      ],
      [
        4505.788,
        6262.7876,
        199.88768
      ],
      [
        4457.928,
        6373.57227,
        241.829056
      ],
      [
        4406.10547,
        6482.465,
        284.0608
      ],
      [
        4354.978,
        6590.331,
        329.589844
      ],
      [
        4292.29639,
        6693.44727,
        368.078979
      ],
      [
        4203.995,
        6771.55664,
        321.881866
      ],
      [
        4109.51758,
        6828.259,
        256.868134
      ],
      [
        4060.61865,
        6933.188,
        233.859131
      ],
      [
        4043.95776,
        7043.15771,
        235.551071
      ],
      [
        4043.95776,
        7043.15771,
        235.551071
      ],
      [
        4023.486,
        7155.203,
        232.923721
      ],
      [
        3910.10083,
        7209.51074,
        233.3794
      ],
      [
        3822.016,
        7299.56,
        254.5058
      ],
      [
        3707.15771,
        7297.38037,
        274.3075
      ],
      [
        3636.493,
        7200.17041,
        287.533966
      ],
      [
        3638.218,
        7077.77344,
        273.905548
      ],
      [
        3680.52661,
        6958.184,
        264.550232
      ],
      [
        3741.52856,
        6845.46338,
        256.1203
      ],
      [
        3808.90869,
        6737.486,
        249.990753
      ],
      [
        3832.54346,
        6617.79834,
        259.154724
      ],
      [
        3757.52954,
        6519.52441,
        283.5457
      ],
      [
        3671.232,
        6434.844,
        324.666962
      ],
      [
        3604.67676,
        6331.92,
        293.732452
      ],
      [
        3537.27515,
        6239.918,
        237.15181
      ],
      [
        3460.94263,
        6185.797,
        150.307861
      ],
      [
        3446.542,
        6177.11865,
        137.934509
      ],
      [
        3404.101,
        6115.48535,
        133.155655
      ],
      [
        3476.10181,
        6012.93164,
        159.069016
      ],
      [
        3551.56567,
        5912.52148,
        172.153992
      ],
      [
        3646.6062,
        5828.676,
        158.844208
      ],
      [
        3760.98315,
        5777.175,
        138.0413
      ],
      [
        3885.00024,
        5754.49756,
        118.13784
      ],
      [
        4004.23535,
        5718.835,
        102.17131
      ],
      [
        4053.88086,
        5606.541,
        84.54411
      ],
      [
        4001.02075,
        5491.455,
        70.17132
      ],
      [
        3935.99536,
        5387.856,
        58.731163
      ],
      [
        3812.524,
        5418.71,
        58.0593147
      ],
      [
        3706.40112,
        5489.434,
        66.02232
      ],
      [
        3599.85938,
        5558.321,
        76.9798355
      ],
      [
        3494.21924,
        5620.353,
        109.49128
      ],
      [
        3372.85913,
        5660.017,
        107.727623
      ],
      [
        3254.904,
        5705.207,
        97.19139
      ],
      [
        3146.535,
        5732.086,
        100.697357
      ],
      [
        3040.3728,
        5674.31055,
        88.69799
      ],
      [
        3065.505,
        5549.944,
        79.10238
      ],
      [
        3051.2085,
        5431.696,
        80.26203
      ],
      [
        2947.51636,
        5500.98,
        75.51516
      ],
      [
        2854.07617,
        5584.428,
        83.09419
      ],
      [
        2888.71069,
        5692.087,
        110.9935
      ],
      [
        2975.49121,
        5781.15137,
        136.1562
      ],
      [
        3057.20264,
        5878.392,
        141.820633
      ],
      [
        3122.81079,
        5987.3833,
        133.485886
      ],
      [
        3187.82935,
        6096.31934,
        118.989128
      ],
      [
        3210.33984,
        6211.094,
        116.540764
      ],
      [
        3147.40186,
        6283.7207,
        119.050682
      ],
      [
        3102.17285,
        6330.897,
        109.787933
      ],
      [
        3016.688,
        6425.6167,
        115.481873
      ],
      [
        2933.49438,
        6521.937,
        105.657509
      ],
      [
        2862.47876,
        6625.86328,
        84.17516
      ],
      [
        2799.45337,
        6734.814,
        63.5225258
      ],
      [
        2756.02563,
        6851.206,
        39.3780937
      ],
      [
        2655.0354,
        6803.19873,
        41.80619
      ],
      [
        2557.042,
        6721.58,
        49.13481
      ],
      [
        2450.05664,
        6654.663,
        56.8635025
      ],
      [
        2341.81714,
        6586.856,
        67.2765656
      ],
      [
        2254.12354,
        6495.314,
        66.69447
      ],
      [
        2212.64575,
        6373.93457,
        68.93451
      ],
      [
        2189.315,
        6252.428,
        76.94169
      ],
      [
        2241.64038,
        6145.968,
        115.049484
      ],
      [
        2264.01343,
        6040.6665,
        123.918007
      ],
      [
        2186.48682,
        5942.026,
        103.458549
      ],
      [
        2116.74683,
        5837.453,
        81.68009
      ],
      [
        2105.538,
        5720.59131,
        75.67052
      ],
      [
        2101.55835,
        5614.58643,
        59.5347137
      ],
      [
        2198.85034,
        5531.62646,
        53.88313
      ],
      [
        2300.72,
        5455.396,
        52.7852325
      ],
      [
        2413.25781,
        5395.362,
        60.1123657
      ],
      [
        2491.25317,
        5295.154,
        57.2850342
      ],
      [
        2548.68018,
        5183.648,
        61.99651
      ],
      [
        2623.9375,
        5085.319,
        68.7050858
      ],
      [
        2740.82983,
        5039.758,
        70.32554
      ],
      [
        2864.30566,
        5007.047,
        72.05346
      ],
      [
        2988.422,
        4979.19238,
        74.60774
      ],
      [
        3097.199,
        4958.384,
        76.80919
      ],
      [
        3167.22729,
        4938.14,
        71.92356
      ],
      [
        3271.76343,
        4910.28467,
        73.01871
      ],
      [
        3399.058,
        4913.259,
        65.7885056
      ],
      [
        3525.02466,
        4918.645,
        52.6029472
      ],
      [
        3523.96826,
        5037.836,
        43.65297
      ],
      [
        3573.62622,
        5028.59131,
        40.4316673
      ],
      [
        3641.55176,
        4921.54248,
        32.71797
      ],
      [
        3635.14722,
        4808.6377,
        32.75224
      ],
      [
        3539.29932,
        4726.689,
        34.6584
      ],
      [
        3444.7937,
        4660.087,
        40.87798
      ],
      [
        3382.60815,
        4549.76,
        51.08198
      ],
      [
        3264.512,
        4557.3,
        58.40952
      ],
      [
        3141.57129,
        4583.69043,
        62.8430138
      ],
      [
        3073.26636,
        4491.80371,
        69.2011642
      ],
      [
        3093.07153,
        4367.954,
        73.99653
      ],
      [
        3174.9707,
        4273.949,
        71.91468
      ],
      [
        3271.62964,
        4190.774,
        73.6216
      ],
      [
        3301.38062,
        4068.21045,
        73.76951
      ],
      [
        3284.79858,
        3954.01465,
        105.0289
      ],
      [
        3261.02637,
        3829.303,
        98.71922
      ],
      [
        3185.39551,
        3728.55933,
        90.86739
      ],
      [
        3187.17017,
        3606.00659,
        87.54411
      ],
      [
        3214.60986,
        3484.14038,
        88.35104
      ],
      [
        3314.6062,
        3437.05859,
        108.8664
      ],
      [
        3425.40869,
        3379.69116,
        111.569534
      ],
      [
        3494.7334,
        3329.55957,
        115.477821
      ],
      [
        3599.89624,
        3257.04956,
        115.138245
      ],
      [
        3659.34985,
        3310.18481,
        108.220428
      ],
      [
        3644.999,
        3436.45581,
        103.623329
      ],
      [
        3638.86743,
        3564.57959,
        100.152466
      ],
      [
        3651.81348,
        3691.3374,
        96.18845
      ],
      [
        3690.56836,
        3812.27026,
        90.69748
      ],
      [
        3729.686,
        3932.25024,
        91.9097
      ],
      [
        3759.94751,
        4055.65918,
        83.3314
      ],
      [
        3797.24414,
        4178.09326,
        74.32105
      ],
      [
        3852.92,
        4287.80566,
        66.3351
      ],
      [
        3956.56567,
        4224.12061,
        91.61448
      ],
      [
        4039.25,
        4175.80859,
        116.562485
      ],
      [
        4159.23047,
        4178.69141,
        127.53508
      ],
      [
        4224.741,
        4287.11328,
        127.111816
      ],
      [
        4303.47559,
        4351.216,
        120.102554
      ],
      [
        4261.17773,
        4470.9126,
        105.737457
      ],
      [
        4230.48438,
        4592.38672,
        87.83628
      ],
      [
        4272.11865,
        4702.127,
        77.3606644
      ],
      [
        4361.694,
        4793.196,
        76.24593
      ],
      [
        4445.76953,
        4888.96436,
        77.72477
      ],
      [
        4510.289,
        4998.877,
        83.64892
      ],
      [
        4500.50537,
        5119.61572,
        94.29247
      ],
      [
        4386.09033,
        5107.73145,
        80.22765
      ],
      [
        4279.638,
        5047.0376,
        52.217556
      ],
      [
        4202.52441,
        4969.103,
        43.93273
      ],
      [
        4122.48975,
        5065.63,
        44.3203926
      ],
      [
        4107.82764,
        5190.478,
        45.91769
      ],
      [
        4110.39258,
        5245.749,
        48.9143753
      ]
    ]
  }
]